{
    "name": "Premium Whings",
    "author": "",
    "items": [],
    "steps": [],
    "details": [],
    "raw": "</font><font color=#009B00>\n\nThis Instruction Manual will teach you how to assemble a:\n 'Premium Whings'\nThe Construction kit. must be between Quality Level  200 and  200.\nAll other pieces must be of AT LEAST that level range... \nAdd them using shift+right-click.\n Add in following order:\n\n 1. Two Handed Edged Weapons Construction Kit. SkillTo Assemble: Weapon Smt:  800 ->  800\n\n 2. Notum Enriched Nano Paste - 2x Layer. SkillTo Assemble: Nano Progra:  400 ->  400\n\n 3. Notum Enriched Nano Paste - 1x Layer. SkillTo Assemble: Nano Progra:  300 ->  300\n\n 4. Optimized Co-Weapon Interface. SkillTo Assemble: Comp. Liter:  600 ->  600\n\n 5. Notum Enriched Nano Paste - 4x Layer. SkillTo Assemble: Nano Progra:  500 ->  500\n\n 6. 4x Layer Carbon-Notum Alloy Blade. SkillTo Assemble: Weapon Smt:  600 ->  600\n\n 7. 8x Layer Carbon-Notum Alloy Blade. SkillTo Assemble: Weapon Smt:  700 ->  700\n\n 8. Long Handle. SkillTo Assemble: Weapon Smt:  750 ->  750"
}